odoo_sentinel/__init__.py
odoo_sentinel/i18n/en/LC_MESSAGES/sentinel.mo
odoo_sentinel/i18n/fr/LC_MESSAGES/sentinel.mo
odoo_sentinel-1.1.0.dist-info/LICENSE.txt
odoo_sentinel-1.1.0.dist-info/METADATA
odoo_sentinel-1.1.0.dist-info/WHEEL
odoo_sentinel-1.1.0.dist-info/entry_points.txt
odoo_sentinel-1.1.0.dist-info/top_level.txt
odoo_sentinel-1.1.0.dist-info/RECORD
