Metadata-Version: 2.1
Name: odoo-sentinel
Version: 1.1.0
Summary: Odoo custom ncurses client for the stock_scanner module
Home-page: UNKNOWN
Author: Sylvain Garancher
Author-email: sylvain.garancher@syleam.fr
License: LICENSE.txt
Platform: UNKNOWN
Requires-Dist: odoorpc
